skip/__init__.py
skip/at_location.py
skip/collection.py
skip/element_template.py
skip/eeschema/__init__.py
skip/eeschema/junction.py
skip/eeschema/label.py
skip/eeschema/lib_symbol.py
skip/eeschema/pin.py
skip/eeschema/text.py
skip/eeschema/wire.py
skip/eeschema/schematic/__init__.py
skip/eeschema/schematic/schematic.py
skip/eeschema/schematic/symbol.py
skip/eeschema/sheet/__init__.py
skip/eeschema/sheet/sheet.py
skip/examples/__init__.py
skip/examples/charlieplex.py
skip/examples/symbols.py
skip/pcbnew/__init__.py
skip/pcbnew/footprint.py
skip/pcbnew/graphical.py
skip/pcbnew/layer.py
skip/pcbnew/net.py
skip/pcbnew/segment.py
skip/pcbnew/pcb/__init__.py
skip/pcbnew/pcb/pcb.py
skip/property/__init__.py
skip/property/property.py
skip/sexp/__init__.py
skip/sexp/parser.py
skip/sexp/sourcefile.py
skip/sexp/util.py
kicad_skip-0.2.5.dist-info/LICENSE
kicad_skip-0.2.5.dist-info/METADATA
kicad_skip-0.2.5.dist-info/WHEEL
kicad_skip-0.2.5.dist-info/top_level.txt
kicad_skip-0.2.5.dist-info/RECORD
