Metadata-Version: 2.1
Name: kicad-skip
Version: 0.2.5
Summary: A friendly way to skip the drudgery and manipulate kicad 7+ s-expression schematic, netlist and PCB files
Author: Pat Deegan
Project-URL: Homepage, https://github.com/psychogenic/kicad-skip
Project-URL: Issues, https://github.com/psychogenic/kicad-skip/issues
Classifier: Programming Language :: Python :: 3
Classifier: License :: OSI Approved :: GNU Lesser General Public License v2 or later (LGPLv2+)
Classifier: Operating System :: OS Independent
Requires-Python: >=3.8
License-File: LICENSE
Requires-Dist: sexpdata >=0.0.3
